Workbook

Sheet 推广总览
A1: M080PRO 磁吸自拍杆｜新品推广总览
A3: 推广参数（黄色可改） | D3: 最近5天日均会话 | F3: 最近5天日均订单 | H3: 最近5天总CVR | J3: 最近2天日均会话 | L3: D15目标会话
A4: SKU | B4: M080PRO | D4: =AVERAGE('数据基线-（5天推广的起跑线，开始执行后不要覆盖或修改）'!G5:G9) | F4: =AVERAGE('数据基线-（5天推广的起跑线，开始执行后不要覆盖或修改）'!F5:F9) | H4: =SUM('数据基线-（5天推广的起跑线，开始执行后不要覆盖或修改）'!F5:F9)/SUM('数据基线-（5天推广的起跑线，开始执行后不要覆盖或修改）'!G5:G9) | J4: =AVERAGE('数据基线-（5天推广的起跑线，开始执行后不要覆盖或修改）'!G8:G9) | L4: ='15天推广计划'!K19
A5: 产品 | B5: 磁吸自拍杆
A6: 计划开始日期 | B6: 46266
A7: 售价 | B7: 23.99
A8: 常规Coupon | B8: 0.1 | D8: 核心判断：最近5天CVR约18.5%，说明产品具备成交能力；当前优先级应是扩大高质量会话。15天推广资源建议约70%用于获取流量，30%用于提升点击与转化。
A9: 站内广告总预算 | B9: =SUM('15天推广计划'!I5:I19) | D9: 推广主线：①用核心关键词、长尾词、竞品ASIN和亚马逊视频广告增加曝光与会话；②用主图、Coupon、A+、兼容说明和视频提高点击与转化；③最后5天把预算集中到5个核心词与最佳素材，形成销量峰值并推动自然排名。
A10: 站外/内容总预算 | B10: =SUM('15天推广计划'!J5:J19)
A11: 推广现金预算合计 | B11: =B9+B10
A13: 三个推广周期与目标
A14: 周期 | B14: 推广重点 | C14: 目标日均会话 | D14: 目标日均订单 | E14: 最低CVR | F14: 站内预算 | G14: 站外预算 | H14: 目标销售额 | I14: 进入下一周期门槛 | J14: 验收重点
A15: 周期1 | B15: Listing＋Coupon＋核心广告＋竞品流量全部启动 | C15: =AVERAGE('15天推广计划'!K5:K9) | D15: =AVERAGE('15天推广计划'!L5:L9) | E15: ='15天推广计划'!N9 | F15: =SUM('15天推广计划'!I5:I9) | G15: =SUM('15天推广计划'!J5:J9) | H15: =SUM('15天推广计划'!M5:M9) | I15: 核心素材和广告入口全部上线 | J15: 是否真正完成了推广基础建设
A16: 周期2 | B16: 放大成交词、长尾场景和亚马逊视频广告 | C16: =AVERAGE('15天推广计划'!K10:K14) | D16: =AVERAGE('15天推广计划'!L10:L14) | E16: ='15天推广计划'!N14 | F16: =SUM('15天推广计划'!I10:I14) | G16: =SUM('15天推广计划'!J10:J14) | H16: =SUM('15天推广计划'!M10:M14) | I16: 日均会话≥80且整体CVR≥15% | J16: 哪个渠道带来了新增订单
A17: 周期3 | B17: 集中预算冲5个核心词排名并制造销量高峰 | C17: =AVERAGE('15天推广计划'!K15:K19) | D17: =AVERAGE('15天推广计划'!L15:L19) | E17: ='15天推广计划'!N19 | F17: =SUM('15天推广计划'!I15:I19) | G17: =SUM('15天推广计划'!J15:J19) | H17: =SUM('15天推广计划'!M15:M19) | I17: 末日会话≥120、订单≥19、CVR≥16% | J17: 流量能否逐步转成自然订单
A19: 15天预计推广结果（目标，不是销量保证）
A20: 15天目标会话合计 | B20: 15天目标订单合计 | C20: 目标销售额 | D20: 站内预算上限 | E20: 站外预算上限 | F20: 现金预算合计 | G20: 现金推广费率 | H20: D15目标日销量
A21: =SUM('15天推广计划'!K5:K19) | B21: =SUM('15天推广计划'!L5:L19) | C21: =SUM('15天推广计划'!M5:M19) | D21: =B9 | E21: =B10 | F21: =B11 | G21: =B11/C21 | H21: ='15天推广计划'!L19
A23: 预算说明：站内广告与站外内容金额均为上限；Coupon折扣成本未计入现金预算。若毛利无法承受10%优惠，应下调Coupon，而不是用亏损订单硬冲销量。

Sheet 15天推广计划
A1: M080PRO 磁吸自拍杆｜15天新品推广计划（5天 × 3周期）
A2: 本表重点：每天具体做哪些推广动作来增加曝光、点击、会话和订单。预算均为上限，不要求必须花完；只有上一周期流量和转化达到门槛，才进入下一周期扩量。
A4: 周期 | B4: 天数 | C4: 日期 | D4: 当天增长目标 | E4: 主要流量渠道 | F4: 具体推广动作 | G4: 需要完成的素材 | H4: 优惠/促销 | I4: 站内广告预算上限 | J4: 站外/内容预算 | K4: 目标会话 | L4: 目标订单 | M4: 目标销售额 | N4: 最低CVR | O4: 预期作用 | P4: 员工当天交付 | Q4: 负责人 | R4: 状态
A5: 周期1｜基础启动 | B5: D1 | C5: =推广总览!$B$6+0 | D5: 确定定位与关键词入口 | E5: 自然搜索准备＋竞品研究 | F5: 1）分析前20个磁吸自拍杆竞品的标题、主图、价格、评分和流量词；2）建立50个关键词库：5个核心词、20个长尾词、15个场景词、10个竞品词；3）确定主推人群与3个购买理由。 | G5: 竞品矩阵、50词关键词库、3条核心卖点 | H5: 保持当前售价；确定D3启用10% Coupon或约$3优惠（二选一，按毛利） | I5: 30 | J5: 0 | K5: 55 | L5: 7 | M5: =L5*推广总览!$B$7 | N5: 0.12 | O5: 让后续广告、Listing和视频围绕同一购买理由，不再分散流量 | P5: 《竞品与关键词调研表》＋推广定位1页 | Q5: 运营员工 | R5: 未开始
A6: 周期1｜基础启动 | B6: D2 | C6: =推广总览!$B$6+1 | D6: 提高搜索点击与页面转化 | E6: 自然搜索＋Listing转化 | F6: 1）标题放入1个核心品类词和2个真实优势；2）主图突出磁吸连接与产品完整形态；3）副图依次讲磁吸稳定、自拍杆长度、三脚架模式、遥控、兼容性、便携场景；4）完善A+和FAQ；5）若符合条件报名Vine，严禁返现或诱导评价。 | G6: 新主图1张、副图6张、A+结构、30秒视频脚本 | H6: D3优惠预设完成但当天先不频繁改价 | I6: 30 | J6: 0 | K6: 60 | L6: 8 | M6: =L6*推广总览!$B$7 | N6: 0.13 | O6: 提升广告与自然搜索的CTR，并减少兼容性疑问导致的跳失 | P6: Listing修改前后截图＋素材完成清单 | Q6: 运营员工 | R6: 未开始
A7: 周期1｜基础启动 | B7: D3 | C7: =推广总览!$B$6+2 | D7: 正式启动核心关键词流量 | E7: SP核心精准＋词组＋自动 | F7: 1）核心精准8–12词，占广告预算40%；2）长尾词组占20%；3）自动紧密/宽泛分开，占15%；4）竞品商品投放占25%；5）核心精准Top of Search从+20%开始；6）记录5个核心词自然位和广告位。 | G7: 广告命名表、关键词分组、5词排名表 | H7: 启用10% Coupon或约$3 Coupon，至少连续保持5天，不与主图同时反复更改 | I7: 30 | J7: 0 | K7: 65 | L7: 9 | M7: =L7*推广总览!$B$7 | N7: 0.14 | O7: 快速增加精准曝光和点击，同时用优惠提高首批成交速度 | P7: 广告上线截图＋预算分配＋5词排名 | Q7: 运营员工 | R7: 未开始
A8: 周期1｜基础启动 | B8: D4 | C8: =推广总览!$B$6+3 | D8: 截取竞品商品页流量 | E8: SP商品投放＋类目投放 | F8: 1）选择20个同形态竞品ASIN，优先价格为本品0.9–1.25倍、评分或素材存在弱点的产品；2）按低价/同价/高价分3组；3）建立细分类目定向并限制价格区间；4）有其他自有相关ASIN时增加品牌防守；5）补充一张对比型副图。 | G8: 竞品ASIN清单20个、3个商品投放组、产品对比图 | H8: 维持D3优惠，不再新增第二种促销 | I8: 30 | J8: 0 | K8: 70 | L8: 10 | M8: =L8*推广总览!$B$7 | N8: 0.14 | O8: 从竞品详情页获取已有购买意图的消费者，提高新增会话质量 | P8: 竞品投放截图＋ASIN筛选理由 | Q8: 运营员工 | R8: 未开始
A9: 周期1｜基础启动 | B9: D5 | C9: =推广总览!$B$6+4 | D9: 启动视频流量并完成首轮推广 | E9: Listing视频＋SBV/品牌内容 | F9: 1）上传30–45秒Listing视频；2）制作3条15秒短视频，主题分别为“磁吸即装”“自拍杆变三脚架”“旅行快速拍摄”；3）有品牌权限则上线核心词视频广告、品牌旗舰店模块或Posts；4）复盘D1–D5各渠道带来的会话和订单。 | G9: Listing视频1条、短视频3条、周期1推广复盘 | H9: 优惠继续；不因单日数据随意关闭 | I9: 30 | J9: 0 | K9: 75 | L9: 11 | M9: =L9*推广总览!$B$7 | N9: 0.15 | O9: 视频展示产品使用过程，扩大点击入口并提高购买理解 | P9: 视频链接/截图＋周期1渠道结果 | Q9: 运营员工 | R9: 未开始
A10: 周期2｜扩大流量 | B10: D6 | C10: =推广总览!$B$6+5 | D10: 放大已验证的成交关键词 | E10: 核心精准关键词 | F10: 1）从前5天筛选有≥2单、CVR≥15%、ACoS≤45%的关键词；2）转入独立精准活动；3）赢家竞价+5%–10%、预算+15%；4）从词组/自动活动中否定精准，避免内部抢流量；5）核心赢家获得当天50%广告预算。 | G10: Top10成交词清单、独立赢家广告组 | H10: 维持原优惠 | I10: 30 | J10: 0 | K10: 80 | L10: 12 | M10: =L10*推广总览!$B$7 | N10: 0.15 | O10: 把预算从试错流量转到真正能带来订单的关键词上 | P10: 旧/新竞价、预算和数据依据 | Q10: 运营员工 | R10: 未开始
A11: 周期2｜扩大流量 | B11: D7 | C11: =推广总览!$B$6+6 | D11: 扩展长尾与使用场景流量 | E11: 长尾精准＋词组广告 | F11: 1）增加20个长尾词；2）按旅行拍摄、桌面拍摄、视频通话/直播、遥控自拍等真实场景分组；3）在A+或副图加入3个高转化场景；4）只有产品真实兼容时才使用compatible with MagSafe、remote等词。 | G11: 20个长尾词、3组场景广告、场景素材3张 | H11: 维持优惠与售价稳定 | I11: 30 | J11: 0 | K11: 85 | L11: 13 | M11: =L11*推广总览!$B$7 | N11: 0.15 | O11: 扩大相关搜索覆盖面，降低只依赖1–2个大词的风险 | P11: 长尾词表＋场景广告截图 | Q11: 运营员工 | R11: 未开始
A12: 周期2｜扩大流量 | B12: D8 | C12: =推广总览!$B$6+7 | D12: 提升广告和自然搜索点击率 | E12: 主图/视频单变量测试 | F12: 1）找出曝光高但CTR低的核心词；2）只测试一个变量：主图或优惠标识二选一；3）上线第2条短视频或视频广告；4）对强相关但曝光不足的精准词小幅提高竞价。 | G12: CTR测试卡、第二条短视频 | H12: 不同时改主图、标题和优惠；测试至少观察48–72小时 | I12: 30 | J12: 0 | K12: 90 | L12: 14 | M12: =L12*推广总览!$B$7 | N12: 0.15 | O12: 同样曝光获得更多点击，使会话增长不完全依靠继续加价 | P12: 测试变量、开始时间、修改前CTR | Q12: 运营员工 | R12: 未开始
A13: 周期2｜扩大流量 | B13: D9 | C13: =推广总览!$B$6+8 | D13: 扩大竞品与商品页覆盖 | E13: 商品投放＋品牌防守 | F13: 1）把已产生点击/订单的ASIN独立出来；2）竞品ASIN扩展到30个；3）增加10个同类但价格更高或评分较弱的商品；4）对自有ASIN做品牌防守；5）Product Pages表现达标后再提高位置系数。 | G13: 30个竞品ASIN库、赢家ASIN独立组 | H13: 维持优惠 | I13: 30 | J13: 0 | K13: 95 | L13: 15 | M13: =L13*推广总览!$B$7 | N13: 0.15 | O13: 扩大高购买意图商品页流量，并减少竞品在自有页面截流 | P13: ASIN新增/淘汰清单＋商品页数据 | Q13: 运营员工 | R13: 未开始
A14: 周期2｜扩大流量 | B14: D10 | C14: =推广总览!$B$6+9 | D14: 放大亚马逊视频广告流量 | E14: SBV/Listing视频广告 | F14: 1）把D5上线的Listing视频和15秒短视频用于核心词视频广告；2）选择CTR/CVR优于SP平均的视频加大投放；3）核心词精准投放，前3秒展示磁吸即装；4）对比视频广告与SP搜索广告的会话、订单和CVR；5）未达标视频暂停或替换素材。 | G14: 视频广告投放组、视频表现对比表 | H14: 维持原优惠 | I14: 30 | J14: 0 | K14: 100 | L14: 15 | M14: =L14*推广总览!$B$7 | N14: 0.15 | O14: 用产品演示视频提高点击质量，扩大站内视频会话与订单 | P14: 视频广告截图＋视频vs SP对比＋周期2复盘 | Q14: 运营员工 | R14: 未开始
A15: 周期3｜销量与排名 | B15: D11 | C15: =推广总览!$B$6+10 | D15: 集中冲5个核心词自然排名 | E15: 核心精准＋Top of Search | F15: 1）只选择5个同时有转化和排名机会的核心词；2）60%广告预算集中到这5个词；3）Top of Search提高到+20%–40%，每次小幅调整；4）上午和晚上各记录一次自然排名；5）其余探索活动控制在总预算10%。 | G15: 5词冲排名表、核心预算分配 | H15: 继续10%优惠，保持价格稳定 | I15: 30 | J15: 0 | K15: 105 | L15: 17 | M15: =L15*推广总览!$B$7 | N15: 0.16 | O15: 用连续订单强化核心词相关性，逐步让自然流量接替广告流量 | P15: 5词早晚排名＋订单归因 | Q15: 运营员工 | R15: 未开始
A16: 周期3｜销量与排名 | B16: D12 | C16: =推广总览!$B$6+11 | D16: 加大视频广告与核心词曝光 | E16: 核心词＋视频再曝光 | F16: 1）加大表现最好的视频广告；2）所有素材统一突出同一主卖点；3）核心词保持稳定竞价，不因单日波动大幅改价；4）核对毛利后维持10% Coupon，不额外加码短期促销。 | G16: 视频复投清单、毛利核对 | H16: 维持10% Coupon，不设72小时加码 | I16: 30 | J16: 0 | K16: 110 | L16: 18 | M16: =L16*推广总览!$B$7 | N16: 0.16 | O16: 用视频和核心词持续拉动销量速度，推动关键词排名 | P16: 视频投放截图＋毛利核对＋销量趋势 | Q16: 运营员工 | R16: 未开始
A17: 周期3｜销量与排名 | B17: D13 | C17: =推广总览!$B$6+12 | D17: 追回浏览未购买人群 | E17: Sponsored Display再营销＋关联销售 | F17: 1）有权限则建立7天/14天浏览再营销；2）把已转化竞品ASIN建立独立商品投放；3）完善FAQ，解决磁吸兼容、遥控连接、长度和稳定性问题；4）品牌旗舰店加入磁吸自拍杆入口和相关产品交叉展示。 | G17: 再营销广告组、FAQ更新、品牌店入口 | H17: 维持10% Coupon | I17: 30 | J17: 0 | K17: 115 | L17: 18 | M17: =L17*推广总览!$B$7 | N17: 0.16 | O17: 提高浏览人群二次触达和转化，增加同品牌关联流量 | P17: 再营销设置＋受众/点击数据 | Q17: 运营员工 | R17: 未开始
A18: 周期3｜销量与排名 | B18: D14 | C18: =推广总览!$B$6+13 | D18: 第二波集中放量 | E18: 核心词＋视频广告 | F18: 1）广告预算分配：核心赢家70%、竞品商品投放20%、探索10%；2）暂停明显无关和连续无转化流量；3）继续投放表现最好的视频广告；4）对5个核心词继续记录排名；5）不在当天多次改竞价。 | G18: 最终预算分配表、视频广告复盘、5词排名 | H18: 维持10% Coupon | I18: 30 | J18: 0 | K18: 125 | L18: 20 | M18: =L18*推广总览!$B$7 | N18: 0.16 | O18: 把前13天验证出的最佳广告、素材和优惠集中形成销量峰值 | P18: 预算分配＋渠道销量贡献 | Q18: 运营员工 | R18: 未开始
A19: 周期3｜销量与排名 | B19: D15 | C19: =推广总览!$B$6+14 | D19: 固化可持续推广结构 | E19: 赢家广告＋自然排名维护 | F19: 1）汇总15天各渠道会话、订单和销量；2）保留核心赢家词、长尾词、赢家ASIN和最佳视频；3）淘汰无效流量入口；4）确定未来30天的固定预算、Coupon和内容节奏；5）对比5个核心词D1与D15自然排名。 | G19: 15天推广总结、稳定广告结构、未来30天推广排期 | H19: 根据自然排名和转化决定维持10% Coupon或调整，不突然大幅涨价 | I19: 30 | J19: 0 | K19: 130 | L19: 21 | M19: =L19*推广总览!$B$7 | N19: 0.16 | O19: 把短期推广转成稳定自然流量与日常销量，而不是活动结束后归零 | P19: 渠道贡献表＋关键词排名对比＋30天计划 | Q19: 运营员工 | R19: 未开始

Sheet 渠道与素材
A1: 推广渠道打法与必备素材清单
A3: 一、流量渠道如何分工
A4: 渠道 | B4: 主要作用 | C4: 具体设置 | D4: 预算建议 | E4: 核心素材 | F4: 看什么指标 | G4: 何时放大
A5: SP核心精准 | B5: 抢核心搜索流量和关键词排名 | C5: 8–12个核心词单独活动；Top of Search从+20%开始 | D5: 站内广告35% | E5: 主图、标题、Coupon | F5: 曝光、CTR、CVR、订单、自然位 | G5: ≥2单、CVR≥15%、ACoS≤45%
A6: SP长尾/词组 | B6: 扩大高相关场景流量 | C6: 旅行、桌面、视频通话、遥控自拍等真实场景分组 | D6: 站内广告15% | E6: 场景副图、A+ | F6: 搜索词、CTR、订单 | G6: 有订单的搜索词迁移精准
A7: SP商品投放 | B7: 截取竞品详情页购买人群 | C7: 低价/同价/高价竞品分组；赢家ASIN独立 | D7: 站内广告20% | E7: 对比图、价格与优惠 | F7: 商品页点击、订单、ASIN表现 | G7: ≥2单且成本达标
A8: 自动探索 | B8: 发现新搜索词和关联商品 | C8: 紧密、宽泛、替代、关联分别出价 | D8: 站内广告10% | E8: 完整Listing | F8: 新搜索词、浪费词、订单 | G8: 只放大已产生订单的词
A9: SBV/视频广告 | B9: 用动态演示提高点击质量 | C9: 前3秒展示磁吸即装；核心词精准投放 | D9: 站内广告10% | E9: 15–30秒产品视频 | F9: 播放、CTR、CVR、订单 | G9: 视频CTR/CVR优于SP平均
A10: Sponsored Display | B10: 追回浏览未购买用户 | C10: 7天/14天浏览再营销，D13后启用 | D10: 站内广告10% | E10: 产品图、优惠 | F10: 点击、订单、再营销成本 | G10: 有足够受众且产生订单
A11: Coupon/短期促销 | B11: 提高搜索点击与购买转化 | C11: 常规10%，贯穿15天；不设72小时加码或15%短期上限 | D11: 折扣成本另算 | E11: 价格、Coupon徽标 | F11: CTR、CVR、销量速度 | G11: 折扣后仍满足最低毛利
A13: 二、Listing与短视频素材清单
A14: 素材 | B14: 必须表达什么 | C14: 画面要求 | D14: 解决的问题 | E14: 完成日 | F14: 负责人 | G14: 验收标准
A15: 主图 | B15: 磁吸自拍杆完整形态和核心结构 | C15: 白底、产品占画面大、配件整齐、不可虚构功能 | D15: 提高搜索CTR | E15: D2 | F15: 美工 | G15: 手机端缩略图仍能看清磁吸结构
A16: 副图1：磁吸 | B16: 如何安装、兼容范围、稳定性 | C16: 近景＋真实手机；吸力数据仅写实测值 | D16: 减少磁吸疑虑 | E16: D2 | F16: 美工 | G16: 一眼看懂安装方式
A17: 副图2：自拍杆 | B17: 展开长度、收纳长度、重量 | C17: 标注真实尺寸并有人物比例 | D17: 证明便携和拍摄距离 | E17: D2 | F17: 美工 | G17: 尺寸与实物/说明书一致
A18: 副图3：三脚架 | B18: 展开方式和桌面/户外稳定场景 | C18: 展示完整脚架落地，不夸大抗风 | D18: 突出多功能价值 | E18: D2 | F18: 美工 | G18: 消费者能看懂如何切换
A19: 副图4：遥控 | B19: 遥控连接与拍照步骤 | C19: 仅产品真实含遥控时制作 | D19: 提升自拍便利感 | E19: D2 | F19: 美工 | G19: 3步以内讲清操作
A20: 副图5：兼容性 | B20: 兼容手机型号/磁吸条件 | C20: 区分原生磁吸与磁环辅助 | D20: 减少退货和差评 | E20: D2 | F20: 美工 | G20: 不使用未经验证的兼容承诺
A21: 副图6：场景 | B21: 旅行、聚会、桌面视频、家庭合影 | C21: 真实自然光和真实使用姿态 | D21: 扩大使用需求 | E21: D7 | F21: 美工 | G21: 至少覆盖3种高频场景
A22: Listing视频 | B22: 磁吸安装→拉伸→三脚架→遥控拍摄 | C22: 30–45秒；前3秒必须出现核心功能 | D22: 提高理解与转化 | E22: D5 | F22: 视频 | G22: 无长时间片头，产品细节一致
A23: 短视频3条 | B23: 磁吸即装、形态切换、旅行拍摄 | C23: 每条约15秒，竖版，结尾有购买理由 | D23: 站内视频广告 | E23: D5 | F23: 视频 | G23: 每条只讲一个卖点
A25: 真实性红线：MagSafe兼容、遥控、长度、重量、承重、吸力、360°等卖点，只有产品真实具备且能证明时才可用于Listing和广告。

Sheet 每日结果回填
A1: 每日推广结果回填（只保留与流量、销量直接相关的数据）
A2: 每天上午回填前一日结果。老板重点看：目标会话是否完成、目标订单是否完成、哪个推广渠道真正带来订单，以及第二天准备放大什么。
A4: 日期 | B4: 周期 | C4: 天数 | D4: 目标会话 | E4: 实际会话 | F4: 会话完成率 | G4: 目标订单 | H4: 实际订单 | I4: 订单完成率 | J4: 实际销售额 | K4: 站内广告花费 | L4: 站外/内容花费 | M4: 实际CVR | N4: 推广费用率 | O4: 核心词排名变化 | P4: 当天最有效渠道 | Q4: 第二天放大动作 | R4: 状态
A5: ='15天推广计划'!C5 | B5: 周期1｜基础启动 | C5: D1 | D5: ='15天推广计划'!K5 | F5: =IF(E5="","",IFERROR(E5/D5,0)) | G5: ='15天推广计划'!L5 | I5: =IF(H5="","",IFERROR(H5/G5,0)) | M5: =IF(E5="","",IFERROR(H5/E5,0)) | N5: =IF(J5="","",IFERROR((K5+L5)/J5,0)) | R5: =IF(E5="","",IF(AND(F5>=1,I5>=1),"达标",IF(OR(F5<0.8,I5<0.8),"未达标","接近目标")))
A6: ='15天推广计划'!C6 | B6: 周期1｜基础启动 | C6: D2 | D6: ='15天推广计划'!K6 | F6: =IF(E6="","",IFERROR(E6/D6,0)) | G6: ='15天推广计划'!L6 | I6: =IF(H6="","",IFERROR(H6/G6,0)) | M6: =IF(E6="","",IFERROR(H6/E6,0)) | N6: =IF(J6="","",IFERROR((K6+L6)/J6,0)) | R6: =IF(E6="","",IF(AND(F6>=1,I6>=1),"达标",IF(OR(F6<0.8,I6<0.8),"未达标","接近目标")))
A7: ='15天推广计划'!C7 | B7: 周期1｜基础启动 | C7: D3 | D7: ='15天推广计划'!K7 | F7: =IF(E7="","",IFERROR(E7/D7,0)) | G7: ='15天推广计划'!L7 | I7: =IF(H7="","",IFERROR(H7/G7,0)) | M7: =IF(E7="","",IFERROR(H7/E7,0)) | N7: =IF(J7="","",IFERROR((K7+L7)/J7,0)) | R7: =IF(E7="","",IF(AND(F7>=1,I7>=1),"达标",IF(OR(F7<0.8,I7<0.8),"未达标","接近目标")))
A8: ='15天推广计划'!C8 | B8: 周期1｜基础启动 | C8: D4 | D8: ='15天推广计划'!K8 | F8: =IF(E8="","",IFERROR(E8/D8,0)) | G8: ='15天推广计划'!L8 | I8: =IF(H8="","",IFERROR(H8/G8,0)) | M8: =IF(E8="","",IFERROR(H8/E8,0)) | N8: =IF(J8="","",IFERROR((K8+L8)/J8,0)) | R8: =IF(E8="","",IF(AND(F8>=1,I8>=1),"达标",IF(OR(F8<0.8,I8<0.8),"未达标","接近目标")))
A9: ='15天推广计划'!C9 | B9: 周期1｜基础启动 | C9: D5 | D9: ='15天推广计划'!K9 | F9: =IF(E9="","",IFERROR(E9/D9,0)) | G9: ='15天推广计划'!L9 | I9: =IF(H9="","",IFERROR(H9/G9,0)) | M9: =IF(E9="","",IFERROR(H9/E9,0)) | N9: =IF(J9="","",IFERROR((K9+L9)/J9,0)) | R9: =IF(E9="","",IF(AND(F9>=1,I9>=1),"达标",IF(OR(F9<0.8,I9<0.8),"未达标","接近目标")))
A10: ='15天推广计划'!C10 | B10: 周期2｜扩大流量 | C10: D6 | D10: ='15天推广计划'!K10 | F10: =IF(E10="","",IFERROR(E10/D10,0)) | G10: ='15天推广计划'!L10 | I10: =IF(H10="","",IFERROR(H10/G10,0)) | M10: =IF(E10="","",IFERROR(H10/E10,0)) | N10: =IF(J10="","",IFERROR((K10+L10)/J10,0)) | R10: =IF(E10="","",IF(AND(F10>=1,I10>=1),"达标",IF(OR(F10<0.8,I10<0.8),"未达标","接近目标")))
A11: ='15天推广计划'!C11 | B11: 周期2｜扩大流量 | C11: D7 | D11: ='15天推广计划'!K11 | F11: =IF(E11="","",IFERROR(E11/D11,0)) | G11: ='15天推广计划'!L11 | I11: =IF(H11="","",IFERROR(H11/G11,0)) | M11: =IF(E11="","",IFERROR(H11/E11,0)) | N11: =IF(J11="","",IFERROR((K11+L11)/J11,0)) | R11: =IF(E11="","",IF(AND(F11>=1,I11>=1),"达标",IF(OR(F11<0.8,I11<0.8),"未达标","接近目标")))
A12: ='15天推广计划'!C12 | B12: 周期2｜扩大流量 | C12: D8 | D12: ='15天推广计划'!K12 | F12: =IF(E12="","",IFERROR(E12/D12,0)) | G12: ='15天推广计划'!L12 | I12: =IF(H12="","",IFERROR(H12/G12,0)) | M12: =IF(E12="","",IFERROR(H12/E12,0)) | N12: =IF(J12="","",IFERROR((K12+L12)/J12,0)) | R12: =IF(E12="","",IF(AND(F12>=1,I12>=1),"达标",IF(OR(F12<0.8,I12<0.8),"未达标","接近目标")))
A13: ='15天推广计划'!C13 | B13: 周期2｜扩大流量 | C13: D9 | D13: ='15天推广计划'!K13 | F13: =IF(E13="","",IFERROR(E13/D13,0)) | G13: ='15天推广计划'!L13 | I13: =IF(H13="","",IFERROR(H13/G13,0)) | M13: =IF(E13="","",IFERROR(H13/E13,0)) | N13: =IF(J13="","",IFERROR((K13+L13)/J13,0)) | R13: =IF(E13="","",IF(AND(F13>=1,I13>=1),"达标",IF(OR(F13<0.8,I13<0.8),"未达标","接近目标")))
A14: ='15天推广计划'!C14 | B14: 周期2｜扩大流量 | C14: D10 | D14: ='15天推广计划'!K14 | F14: =IF(E14="","",IFERROR(E14/D14,0)) | G14: ='15天推广计划'!L14 | I14: =IF(H14="","",IFERROR(H14/G14,0)) | M14: =IF(E14="","",IFERROR(H14/E14,0)) | N14: =IF(J14="","",IFERROR((K14+L14)/J14,0)) | R14: =IF(E14="","",IF(AND(F14>=1,I14>=1),"达标",IF(OR(F14<0.8,I14<0.8),"未达标","接近目标")))
A15: ='15天推广计划'!C15 | B15: 周期3｜销量与排名 | C15: D11 | D15: ='15天推广计划'!K15 | F15: =IF(E15="","",IFERROR(E15/D15,0)) | G15: ='15天推广计划'!L15 | I15: =IF(H15="","",IFERROR(H15/G15,0)) | M15: =IF(E15="","",IFERROR(H15/E15,0)) | N15: =IF(J15="","",IFERROR((K15+L15)/J15,0)) | R15: =IF(E15="","",IF(AND(F15>=1,I15>=1),"达标",IF(OR(F15<0.8,I15<0.8),"未达标","接近目标")))
A16: ='15天推广计划'!C16 | B16: 周期3｜销量与排名 | C16: D12 | D16: ='15天推广计划'!K16 | F16: =IF(E16="","",IFERROR(E16/D16,0)) | G16: ='15天推广计划'!L16 | I16: =IF(H16="","",IFERROR(H16/G16,0)) | M16: =IF(E16="","",IFERROR(H16/E16,0)) | N16: =IF(J16="","",IFERROR((K16+L16)/J16,0)) | R16: =IF(E16="","",IF(AND(F16>=1,I16>=1),"达标",IF(OR(F16<0.8,I16<0.8),"未达标","接近目标")))
... A19: ='15天推广计划'!C19 | B19: 周期3｜销量与排名 | C19: D15 | D19: ='15天推广计划'!K19 | F19: =IF(E19="","",IFERROR(E19/D19,0)) | G19: ='15天推广计划'!L19 | I19: =IF(H19="","",IFERROR(H19/G19,0)) | M19: =IF(E19="","",IFERROR(H19/E19,0)) | N19: =IF(J19="","",IFERROR((K19+L19)/J19,0)) | R19: =IF(E19="","",IF(AND(F19>=1,I19>=1),"达标",IF(OR(F19<0.8,I19<0.8),"未达标","接近目标")))

Sheet 数据基线-（5天推广的起跑线，开始执行后不要覆盖或修改）
A1: M080PRO 最近5天推广数据基线（来自用户截图）
A2: 用途：只用于确定推广起点。最近5天整体转化率不差，真正需要提升的是高质量会话数；但最近2天流量和转化同时下滑，因此推广必须同时兼顾“拉流量”和“保转化”。
A4: 日期 | B4: 广告销售额 | C4: 广告订单 | D4: 广告花费 | E4: 总销售额 | F4: 总订单 | G4: 会话数 | H4: CVR | I4: ACoS | J4: TACoS
A5: 46259 | B5: 119.45 | C5: 5 | D5: 35.81 | E5: 549.47 | F5: 23 | G5: 95 | H5: =IFERROR(F5/G5,0) | I5: =IFERROR(D5/B5,0) | J5: =IFERROR(D5/E5,0)
A6: 46260 | B6: 95.56 | C6: 4 | D6: 44.42 | E6: 406.13 | F6: 17 | G6: 87 | H6: =IFERROR(F6/G6,0) | I6: =IFERROR(D6/B6,0) | J6: =IFERROR(D6/E6,0)
A7: 46261 | B7: 167.23 | C7: 7 | D7: 49.38 | E7: 262.79 | F7: 11 | G7: 60 | H7: =IFERROR(F7/G7,0) | I7: =IFERROR(D7/B7,0) | J7: =IFERROR(D7/E7,0)
A8: 46262 | B8: 23.89 | C8: 1 | D8: 35.82 | E8: 119.45 | F8: 5 | G8: 43 | H8: =IFERROR(F8/G8,0) | I8: =IFERROR(D8/B8,0) | J8: =IFERROR(D8/E8,0)
A9: 46263 | B9: 71.67 | C9: 3 | D9: 44.93 | E9: 119.45 | F9: 5 | G9: 44 | H9: =IFERROR(F9/G9,0) | I9: =IFERROR(D9/B9,0) | J9: =IFERROR(D9/E9,0)
A11: 基线结论
A12: 指标 | B12: 结果 | D12: 最近5天日均约66个会话、12.2单、总CVR约18.5%；但最近2天日均会话只有43.5、日均5单。推广主任务不是继续做复杂报表，而是恢复并扩大曝光、点击和会话，同时把整体CVR保持在15%左右。
A13: 最近5天日均会话 | B13: =AVERAGE(G5:G9)
A14: 最近5天日均订单 | B14: =AVERAGE(F5:F9)
A15: 最近5天总CVR | B15: =SUM(F5:F9)/SUM(G5:G9)
A16: 最近2天日均会话 | B16: =AVERAGE(G8:G9)
